<annotation>
	<folder>wba-15196-000-c023</folder>
	<filename>1150-wba15196000c023-20191101170925-middle.jpg</filename>
	<path>/Users/kratik/Desktop/wba-15196-000-c023/1150-wba15196000c023-20191101170925-middle.jpg</path>
	<source>
		<database>Unknown</database>
	</source>
	<size>
		<width>2592</width>
		<height>1944</height>
		<depth>3</depth>
	</size>
	<segmented>0</segmented>
	<object>
		<name>shelf</name>
		<pose>Unspecified</pose>
		<truncated>0</truncated>
		<difficult>0</difficult>
		<bndbox>
			<xmin>442</xmin>
			<ymin>176</ymin>
			<xmax>1793</xmax>
			<ymax>857</ymax>
		</bndbox>
	</object>
	<object>
		<name>shelf</name>
		<pose>Unspecified</pose>
		<truncated>0</truncated>
		<difficult>0</difficult>
		<bndbox>
			<xmin>458</xmin>
			<ymin>879</ymin>
			<xmax>1766</xmax>
			<ymax>1579</ymax>
		</bndbox>
	</object>
</annotation>
