<annotation>
	<folder>shelf images</folder>
	<filename>tgt-t3203-c34-c006_1569487980_1-cap1_23.jpg</filename>
	<path>C:\Users\nshan\Documents\shelf images\tgt-t3203-c34-c006_1569487980_1-cap1_23.jpg</path>
	<source>
		<database>Unknown</database>
	</source>
	<size>
		<width>2592</width>
		<height>1944</height>
		<depth>3</depth>
	</size>
	<segmented>0</segmented>
	<object>
		<name>shelf</name>
		<pose>Unspecified</pose>
		<truncated>0</truncated>
		<difficult>0</difficult>
		<bndbox>
			<xmin>332</xmin>
			<ymin>227</ymin>
			<xmax>1973</xmax>
			<ymax>772</ymax>
		</bndbox>
	</object>
	<object>
		<name>shelf</name>
		<pose>Unspecified</pose>
		<truncated>0</truncated>
		<difficult>0</difficult>
		<bndbox>
			<xmin>376</xmin>
			<ymin>710</ymin>
			<xmax>1970</xmax>
			<ymax>1310</ymax>
		</bndbox>
	</object>
	<object>
		<name>shelf</name>
		<pose>Unspecified</pose>
		<truncated>0</truncated>
		<difficult>0</difficult>
		<bndbox>
			<xmin>432</xmin>
			<ymin>1245</ymin>
			<xmax>1950</xmax>
			<ymax>1789</ymax>
		</bndbox>
	</object>
</annotation>
